get_oxidation_states/__init__.py
get_oxidation_states/__main__.py
get_oxidation_states/server.py
get_oxidation_states-0.2.0.dist-info/METADATA
get_oxidation_states-0.2.0.dist-info/WHEEL
get_oxidation_states-0.2.0.dist-info/entry_points.txt
get_oxidation_states-0.2.0.dist-info/licenses/LICENSE
get_oxidation_states-0.2.0.dist-info/RECORD
