Metadata-Version: 2.4
Name: get-oxidation-states
Version: 0.2.0
Summary: MCP server for querying common oxidation states and stability of chemical elements
Author: WangGroup, XMU.
Maintainer-email: Wangdu Phunsukh <wangduphunsukh246@gmail.com>
License: MIT
License-File: LICENSE
Keywords: chemistry,mcp,model context protocol,oxidation states
Classifier: Development Status :: 4 - Beta
Classifier: Intended Audience :: Developers
Classifier: License :: OSI Approved :: MIT License
Classifier: Programming Language :: Python :: 3.11
Requires-Python: >=3.11
Requires-Dist: httpx>=0.28.1
Requires-Dist: mcp>=1.25.0
Requires-Dist: pydantic>=2.12.5
Requires-Dist: pytest-asyncio>=1.3.0
Requires-Dist: pytest>=9.0.2
Requires-Dist: types-python-dateutil>=2.9.0.20251115
Requires-Dist: typing-extensions>=4.15.0
